{"frameRate":30,"name":"Dress","version":"5.5","compatibleVersion":"5.5","armature":[{"type":"Armature","frameRate":30,"name":"Dress","aabb":{"x":-729.25,"y":-151.57,"width":1627.9,"height":719.82},"bone":[{"name":"root"},{"name":"Layer 18","parent":"root","transform":{"x":-26.25,"y":86.25}},{"name":"Layer 17","parent":"root","transform":{"x":80.8,"y":340.65}},{"name":"scat","parent":"root","transform":{"x":30.85,"y":345.5}},{"name":"Layer 15","parent":"root","transform":{"x":555.85,"y":316.85,"scX":-1}},{"name":"cat4","parent":"root","transform":{"x":175.45,"y":366.5}},{"name":"cat3","parent":"root","transform":{"x":274.3,"y":366.5}},{"name":"cat2","parent":"root","transform":{"x":372.8,"y":366.5}},{"name":"cat1","parent":"root","transform":{"x":471.65,"y":366.5}},{"name":"panel_cl","parent":"root","transform":{"x":40.9,"y":56.25}},{"name":"menu_bt_cl","parent":"root","transform":{"x":325,"y":11.75}},{"name":"back_bt","parent":"root","transform":{"x":325.2,"y":440.4}},{"name":"train_bt","parent":"root","transform":{"x":462.6,"y":397.95}},{"name":"shop_bt","parent":"root","transform":{"x":-80.75,"y":397.95}},{"name":"zone_cards_about","parent":"root"},{"name":"about_cl","parent":"root","transform":{"x":319.75,"y":163.55}},{"name":"shop_cl","parent":"root","transform":{"x":309.95,"y":214.45}},{"name":"zone_tuto","parent":"root"},{"name":"zone_drag","parent":"root"}],"slot":[{"name":"Layer 18","parent":"Layer 18"},{"name":"Layer 17","parent":"Layer 17"},{"name":"scat","parent":"scat"},{"name":"Layer 15","parent":"Layer 15"},{"name":"cat4","parent":"cat4"},{"name":"cat3","parent":"cat3"},{"name":"cat2","parent":"cat2"},{"name":"cat1","parent":"cat1"},{"name":"panel_cl","parent":"panel_cl"},{"name":"menu_bt_cl","parent":"menu_bt_cl"},{"name":"back_bt","parent":"back_bt"},{"name":"train_bt","parent":"train_bt"},{"name":"shop_bt","parent":"shop_bt"},{"name":"zone_cards_about","parent":"zone_cards_about"},{"name":"about_cl","parent":"about_cl"},{"name":"shop_cl","parent":"shop_cl"},{"name":"zone_tuto","parent":"zone_tuto"},{"name":"zone_drag","parent":"zone_drag"}],"skin":[{"slot":[{"name":"zone_tuto","display":[{"name":"Symbol 206","transform":{"x":-38.9,"y":-38}}]},{"name":"zone_drag","display":[{"name":"Symbol 206","transform":{"x":-38.9,"y":-38}}]},{"name":"cat2","display":[{"name":"cat_drag_mc","transform":{"x":0.05,"y":0.5}}]},{"name":"about_cl","display":[{"type":"armature","name":"Symbol 3103"}]},{"name":"Layer 17","display":[{"name":"Symbol 3044","transform":{"x":7,"y":-19}}]},{"name":"cat4","display":[{"name":"cat_drag_mc","transform":{"x":0.05,"y":0.5}}]},{"name":"cat1","display":[{"name":"cat_drag_mc","transform":{"x":0.05,"y":0.5}}]},{"name":"back_bt","display":[{"name":"Symbol 3084","transform":{"x":0.1,"y":-3.3}}]},{"name":"zone_cards_about","display":[{"name":"Symbol 206","transform":{"x":-38.9,"y":-38}}]},{"name":"Layer 18","display":[{"name":"Symbol 3042","transform":{"x":23.5,"y":134}}]},{"name":"train_bt","display":[{"name":"Symbol 3089","transform":{"x":134.55,"y":7.55}}]},{"name":"panel_cl","display":[{"type":"armature","name":"Symbol 3078"}]},{"name":"cat3","display":[{"name":"cat_drag_mc","transform":{"x":0.05,"y":0.5}}]},{"name":"menu_bt_cl","display":[{"name":"Symbol 2888","transform":{"x":0.35,"y":1.45}}]},{"name":"Layer 15","display":[{"name":"Symbol 3052","transform":{"x":9.9,"y":-17.4}}]},{"name":"scat","display":[{"type":"armature","name":"Symbol 3050"}]},{"name":"shop_cl","display":[{"type":"armature","name":"Symbol 3125"}]},{"name":"shop_bt","display":[{"name":"Symbol 3092","transform":{"x":130.85,"y":22.05}}]}]}],"animation":[{"duration":0,"fadeInTime":0.3,"name":"Dress","slot":[{"name":"Layer 17","colorFrame":[{"duration":0,"value":{"rM":89,"gM":89,"bM":89,"rO":24,"gO":14,"bO":5}}]}]}],"defaultActions":[{"gotoAndPlay":"Dress"}]},{"type":"Armature","frameRate":30,"name":"Symbol 3050","aabb":{"x":-47.6,"y":-22.8,"width":75.8,"height":70.97},"bone":[{"name":"root"},{"name":"Layer 3","parent":"root","transform":{"x":-1.3,"y":42,"scX":1.11,"scY":1.11}},{"name":"Layer 2","parent":"root"},{"name":"Layer 1","parent":"root","transform":{"x":0.2,"y":0.15}}],"slot":[{"name":"Layer 3","parent":"Layer 3"},{"name":"Layer 2","parent":"Layer 2"},{"name":"Layer 1","parent":"Layer 1"}],"skin":[{"slot":[{"name":"Layer 1","display":[{"name":"Symbol 3049","transform":{"x":0.5,"y":0.05}}]},{"name":"Layer 2","display":[{"name":"Symbol 3047","transform":{"x":-13.6,"y":23.1}}]},{"name":"Layer 3","display":[{"name":"Symbol 3046","transform":{"x":0.3,"y":0.15}}]}]}],"animation":[{"duration":127,"name":"unnamed","bone":[{"name":"Layer 1","translateFrame":[{"duration":50},{"x":-0.15,"y":-0.05},{"x":-0.3,"y":-0.1},{"x":-0.4,"y":-0.15},{"x":-0.55,"y":-0.2},{"x":-0.7,"y":-0.25},{"x":-0.85,"y":-0.25},{"x":-1,"y":-0.3},{"x":-1.15,"y":-0.35},{"x":-1.25,"y":-0.4},{"x":-1.4,"y":-0.45},{"x":-1.6,"y":-0.45},{"x":-1.8,"y":-0.55},{"duration":48,"x":-1.75,"y":-0.5},{"x":-1.8,"y":-0.55},{"x":-1.7,"y":-0.45},{"x":-1.55,"y":-0.5},{"x":-1.5,"y":-0.45},{"x":-1.4,"y":-0.45},{"x":-1.25,"y":-0.35},{"x":-1.15,"y":-0.35},{"x":-1.05,"y":-0.25},{"x":-0.95,"y":-0.3},{"x":-0.85,"y":-0.25},{"x":-0.7,"y":-0.25},{"x":-0.6,"y":-0.15},{"x":-0.5,"y":-0.15},{"x":-0.4,"y":-0.1},{"x":-0.3,"y":-0.1},{"x":-0.2},{"x":-0.1},{"duration":0}],"rotateFrame":[{"duration":50},{"rotate":-0.5},{"rotate":-1.01},{"rotate":-1.51},{"rotate":-2.02},{"rotate":-2.52},{"rotate":-3.03},{"rotate":-3.53},{"rotate":-4.04},{"rotate":-4.54},{"rotate":-5.05},{"rotate":-5.55},{"rotate":-6.22},{"duration":48,"rotate":-6.06},{"rotate":-6.22},{"rotate":-5.78},{"rotate":-5.31},{"rotate":-5.03},{"rotate":-4.75},{"rotate":-4.29},{"rotate":-4.01},{"rotate":-3.54},{"rotate":-3.26},{"rotate":-2.79},{"rotate":-2.52},{"rotate":-2.05},{"rotate":-1.77},{"rotate":-1.3},{"rotate":-1.02},{"rotate":-0.56},{"rotate":-0.28},{"duration":0}]}]}],"defaultActions":[{"gotoAndPlay":"unnamed"}]},{"type":"Armature","frameRate":30,"name":"Symbol 3078","aabb":{"x":-21.55,"y":-49.8,"width":612,"height":288},"bone":[{"name":"root"},{"name":"bg","parent":"root"},{"name":"sort_1","parent":"root","transform":{"x":24.8,"y":-30.8}},{"name":"sort_2","parent":"root","transform":{"x":59.85,"y":-30.8}},{"name":"sort_3","parent":"root","transform":{"x":94.85,"y":-30.8}},{"name":"radio_1","parent":"root","transform":{"x":248.5,"y":211.05}},{"name":"radio_2","parent":"root","transform":{"x":275.35,"y":211.05}},{"name":"radio_3","parent":"root","transform":{"x":301.95,"y":211.05}},{"name":"about_bt","parent":"root","transform":{"x":514.5,"y":-30.8}},{"name":"zoom_bt","parent":"root","transform":{"x":549.5,"y":-30.8}},{"name":"card_1","parent":"root","transform":{"x":32.15,"y":44.55}},{"name":"card_8","parent":"root","transform":{"x":32.15,"y":147.4}},{"name":"card_2","parent":"root","transform":{"x":116.15,"y":44.55}},{"name":"card_9","parent":"root","transform":{"x":116.15,"y":147.4}},{"name":"card_3","parent":"root","transform":{"x":200.15,"y":44.55}},{"name":"card_10","parent":"root","transform":{"x":200.15,"y":147.4}},{"name":"card_4","parent":"root","transform":{"x":284.15,"y":44.55}},{"name":"card_11","parent":"root","transform":{"x":284.15,"y":147.4}},{"name":"card_5","parent":"root","transform":{"x":368.15,"y":44.55}},{"name":"card_12","parent":"root","transform":{"x":368.15,"y":147.4}},{"name":"card_6","parent":"root","transform":{"x":452.15,"y":44.55}},{"name":"card_13","parent":"root","transform":{"x":452.15,"y":147.4}},{"name":"card_7","parent":"root","transform":{"x":536.15,"y":44.55}},{"name":"card_14","parent":"root","transform":{"x":536.15,"y":147.4}}],"slot":[{"name":"bg","parent":"bg"},{"name":"sort_1","parent":"sort_1"},{"name":"sort_2","parent":"sort_2"},{"name":"sort_3","parent":"sort_3"},{"name":"radio_1","parent":"radio_1"},{"name":"radio_2","parent":"radio_2"},{"name":"radio_3","parent":"radio_3"},{"name":"about_bt","parent":"about_bt"},{"name":"zoom_bt","parent":"zoom_bt"},{"name":"card_1","parent":"card_1"},{"name":"card_8","parent":"card_8"},{"name":"card_2","parent":"card_2"},{"name":"card_9","parent":"card_9"},{"name":"card_3","parent":"card_3"},{"name":"card_10","parent":"card_10"},{"name":"card_4","parent":"card_4"},{"name":"card_11","parent":"card_11"},{"name":"card_5","parent":"card_5"},{"name":"card_12","parent":"card_12"},{"name":"card_6","parent":"card_6"},{"name":"card_13","parent":"card_13"},{"name":"card_7","parent":"card_7"},{"name":"card_14","parent":"card_14"}],"skin":[{"slot":[{"name":"card_9","display":[{"name":"card_mc","transform":{"x":0.05,"y":0.05}}]},{"name":"card_13","display":[{"name":"card_mc","transform":{"x":0.05,"y":0.05}}]},{"name":"radio_2","display":[{"type":"armature","name":"radio"}]},{"name":"card_10","display":[{"name":"card_mc","transform":{"x":0.05,"y":0.05}}]},{"name":"card_14","display":[{"name":"card_mc","transform":{"x":0.05,"y":0.05}}]},{"name":"about_bt","display":[{"name":"Symbol 3071","transform":{"x":-1.55,"y":2.2}}]},{"name":"bg","display":[{"name":"Symbol 3053","transform":{"x":284.45,"y":94.2}}]},{"name":"card_1","display":[{"name":"card_mc","transform":{"x":0.05,"y":0.05}}]},{"name":"sort_1","display":[{"name":"Symbol 3056","transform":{"x":2.95,"y":2.2}}]},{"name":"sort_2","display":[{"name":"Symbol 3059","transform":{"x":2.95,"y":2.2}}]},{"name":"card_2","display":[{"name":"card_mc","transform":{"x":0.05,"y":0.05}}]},{"name":"card_6","display":[{"name":"card_mc","transform":{"x":0.05,"y":0.05}}]},{"name":"radio_1","display":[{"type":"armature","name":"radio"}]},{"name":"card_3","display":[{"name":"card_mc","transform":{"x":0.05,"y":0.05}}]},{"name":"card_7","display":[{"name":"card_mc","transform":{"x":0.05,"y":0.05}}]},{"name":"radio_3","display":[{"type":"armature","name":"radio"}]},{"name":"card_4","display":[{"name":"card_mc","transform":{"x":0.05,"y":0.05}}]},{"name":"zoom_bt","display":[{"type":"armature","name":"SFKLeague_fla.кнопкалупапримерочная_531"}]},{"name":"card_11","display":[{"name":"card_mc","transform":{"x":0.05,"y":0.05}}]},{"name":"card_5","display":[{"name":"card_mc","transform":{"x":0.05,"y":0.05}}]},{"name":"card_8","display":[{"name":"card_mc","transform":{"x":0.05,"y":0.05}}]},{"name":"card_12","display":[{"name":"card_mc","transform":{"x":0.05,"y":0.05}}]},{"name":"sort_3","display":[{"name":"Symbol 3062","transform":{"x":2.45,"y":2.2}}]}]}],"animation":[{"duration":0,"fadeInTime":0.3,"name":"panel_cl"}],"defaultActions":[{"gotoAndPlay":"panel_cl"}]},{"type":"Armature","frameRate":30,"name":"Symbol 3103","aabb":{"x":-326.05,"y":-165.5,"width":1085.45,"height":592.23},"bone":[{"name":"root"},{"name":"Layer 20","parent":"root","transform":{"x":-1.05,"y":59.5,"scX":1.16,"scY":1.17}},{"name":"Layer 19","parent":"root","transform":{"x":6,"y":58.25}},{"name":"close_bt","parent":"root","transform":{"x":294.8,"y":-148.4}},{"name":"slot_1","parent":"root","transform":{"x":-159,"y":-88.05}},{"name":"slot_9","parent":"root","transform":{"x":129,"y":-88.05}},{"name":"slot_2","parent":"root","transform":{"x":-159,"y":-39.85}},{"name":"slot_10","parent":"root","transform":{"x":129,"y":-39.85}},{"name":"slot_3","parent":"root","transform":{"x":-159,"y":9.35}},{"name":"slot_11","parent":"root","transform":{"x":129,"y":9.35}},{"name":"slot_4","parent":"root","transform":{"x":-159,"y":57.55}},{"name":"slot_12","parent":"root","transform":{"x":129,"y":57.55}},{"name":"slot_5","parent":"root","transform":{"x":-159,"y":105.4}},{"name":"slot_13","parent":"root","transform":{"x":129,"y":105.4}},{"name":"slot_6","parent":"root","transform":{"x":623,"y":402.85}},{"name":"slot_14","parent":"root","transform":{"x":129,"y":153.6}},{"name":"slot_7","parent":"root","transform":{"x":-159,"y":153.6}},{"name":"slot_15","parent":"root","transform":{"x":129,"y":202.8}},{"name":"slot_8","parent":"root","transform":{"x":-159,"y":202.8}},{"name":"Layer 2","parent":"root","transform":{"x":5.7,"y":-146.3}},{"name":"Layer 1","parent":"root","transform":{"x":0.05,"y":-144.5}}],"slot":[{"name":"Layer 20","parent":"Layer 20"},{"name":"Layer 19","parent":"Layer 19"},{"name":"close_bt","parent":"close_bt"},{"name":"slot_1","parent":"slot_1"},{"name":"slot_9","parent":"slot_9"},{"name":"slot_2","parent":"slot_2"},{"name":"slot_10","parent":"slot_10"},{"name":"slot_3","parent":"slot_3"},{"name":"slot_11","parent":"slot_11"},{"name":"slot_4","parent":"slot_4"},{"name":"slot_12","parent":"slot_12"},{"name":"slot_5","parent":"slot_5"},{"name":"slot_13","parent":"slot_13"},{"name":"slot_6","parent":"slot_6"},{"name":"slot_14","parent":"slot_14"},{"name":"slot_7","parent":"slot_7"},{"name":"slot_15","parent":"slot_15"},{"name":"slot_8","parent":"slot_8"},{"name":"Layer 2","parent":"Layer 2"},{"name":"Layer 1","parent":"Layer 1"}],"skin":[{"slot":[{"name":"slot_8","display":[{"type":"armature","name":"Symbol 3100"}]},{"name":"slot_12","display":[{"type":"armature","name":"Symbol 3100"}]},{"name":"Layer 2","display":[{"name":"__dbTextures/Symbol 3103/Layer 2_0","transform":{"x":0.35,"y":0.3}}]},{"name":"slot_7","display":[{"type":"armature","name":"Symbol 3100"}]},{"name":"Layer 20","display":[{"name":"Symbol 2077"}]},{"name":"slot_2","display":[{"type":"armature","name":"Symbol 3100"}]},{"name":"slot_6","display":[{"type":"armature","name":"Symbol 3100"}]},{"name":"close_bt","display":[{"name":"Symbol 3095","transform":{"x":13.5,"y":19.9}}]},{"name":"slot_3","display":[{"type":"armature","name":"Symbol 3100"}]},{"name":"slot_9","display":[{"type":"armature","name":"Symbol 3100"}]},{"name":"slot_4","display":[{"type":"armature","name":"Symbol 3100"}]},{"name":"slot_14","display":[{"type":"armature","name":"Symbol 3100"}]},{"name":"slot_5","display":[{"type":"armature","name":"Symbol 3100"}]},{"name":"Layer 1","display":[{"name":"位图 6"}]},{"name":"slot_15","display":[{"type":"armature","name":"Symbol 3100"}]},{"name":"slot_13","display":[{"type":"armature","name":"Symbol 3100"}]},{"name":"Layer 19","display":[{"name":"__dbTextures/Symbol 3103/Layer 19_0","transform":{"x":0.3}}]},{"name":"slot_10","display":[{"type":"armature","name":"Symbol 3100"}]},{"name":"slot_1","display":[{"type":"armature","name":"Symbol 3100"}]},{"name":"slot_11","display":[{"type":"armature","name":"Symbol 3100"}]}]}],"animation":[{"duration":0,"fadeInTime":0.3,"name":"about_cl","slot":[{"name":"slot_6","colorFrame":[{"duration":0,"value":{"aM":0}}]},{"name":"Layer 20","colorFrame":[{"duration":0,"value":{"aM":50}}]}]}],"defaultActions":[{"gotoAndPlay":"about_cl"}]},{"type":"Armature","frameRate":30,"name":"Symbol 3125","aabb":{"x":-327.05,"y":-219.5,"width":650,"height":450},"bone":[{"name":"root"},{"name":"Layer 23","parent":"root","transform":{"x":-2.05,"y":5.5,"scX":1.16,"scY":1.17}},{"name":"Layer 22","parent":"root","transform":{"x":14.75,"y":39.75}},{"name":"Layer 21","parent":"root","transform":{"x":-90.6,"y":-115.75,"skX":-6.05,"skY":-6.05,"scX":-1.33,"scY":1.33}},{"name":"Layer 20","parent":"root","transform":{"x":-12.1,"y":-138.45,"scX":-1.33,"scY":1.33}},{"name":"Layer 19","parent":"root","transform":{"x":117.55,"y":-117.9,"skX":12.23,"skY":12.23,"scX":1.33,"scY":1.33}},{"name":"Layer 18","parent":"root","transform":{"x":60.7,"y":-151.45,"scX":1.33,"scY":1.33}},{"name":"Layer 17","parent":"root"},{"name":"close_bt","parent":"root","transform":{"x":235.4,"y":-103.9}},{"name":"zoom_bt","parent":"root","transform":{"x":219.25,"y":129.45,"scX":1.11,"scY":1.11}},{"name":"Layer 14","parent":"root"},{"name":"money_tx","parent":"root","transform":{"x":42.35,"y":-70}},{"name":"Layer 12","parent":"root","transform":{"x":-28.35,"y":-75.3,"skX":-32.47,"skY":-32.47,"scX":-1}},{"name":"Layer 11","parent":"root","transform":{"x":-21.35,"y":-70.9,"skX":-10.97,"skY":-10.97,"scX":-1}},{"name":"Layer 10","parent":"root","transform":{"x":16.85,"y":-109.8}},{"name":"Layer 9","parent":"root"},{"name":"Layer 8","parent":"root","transform":{"x":-186.55,"y":131.45}},{"name":"Layer 7","parent":"root","transform":{"x":-43.05,"y":133.6}},{"name":"des_tx","parent":"root","transform":{"x":-19.6,"y":132.85}},{"name":"slot_1","parent":"root","transform":{"x":-163.45,"y":-3.05}},{"name":"slot_2","parent":"root","transform":{"x":-75,"y":-3.05}},{"name":"slot_3","parent":"root","transform":{"x":13,"y":-3.05}},{"name":"slot_4","parent":"root","transform":{"x":101,"y":-3.05}},{"name":"slot_5","parent":"root","transform":{"x":189,"y":-3.05}}],"slot":[{"name":"Layer 23","parent":"Layer 23"},{"name":"Layer 22","parent":"Layer 22"},{"name":"Layer 21","parent":"Layer 21"},{"name":"Layer 20","parent":"Layer 20"},{"name":"Layer 19","parent":"Layer 19"},{"name":"Layer 18","parent":"Layer 18"},{"name":"Layer 17","parent":"Layer 17"},{"name":"close_bt","parent":"close_bt"},{"name":"zoom_bt","parent":"zoom_bt"},{"name":"Layer 14","parent":"Layer 14"},{"name":"money_tx","parent":"money_tx"},{"name":"Layer 12","parent":"Layer 12"},{"name":"Layer 11","parent":"Layer 11"},{"name":"Layer 10","parent":"Layer 10"},{"name":"Layer 9","parent":"Layer 9"},{"name":"Layer 8","parent":"Layer 8"},{"name":"Layer 7","parent":"Layer 7"},{"name":"des_tx","parent":"des_tx"},{"name":"slot_1","parent":"slot_1"},{"name":"slot_2","parent":"slot_2"},{"name":"slot_3","parent":"slot_3"},{"name":"slot_4","parent":"slot_4"},{"name":"slot_5","parent":"slot_5"}],"skin":[{"slot":[{"name":"slot_4","display":[{"type":"armature","name":"Symbol 3124"}]},{"name":"des_tx","display":[{"name":"位图 4"}]},{"name":"Layer 17","display":[{"name":"Symbol 3105","transform":{"x":15.05,"y":22.5}}]},{"name":"slot_2","display":[{"type":"armature","name":"Symbol 3124"}]},{"name":"zoom_bt","display":[{"type":"armature","name":"Symbol 3077"}]},{"name":"Layer 22","display":[{"name":"__dbTextures/Symbol 3125/Layer 22_0","transform":{"x":0.5,"y":0.4}}]},{"name":"slot_1","display":[{"type":"armature","name":"Symbol 3124"}]},{"name":"Layer 9","display":[{"name":"Symbol 3109","transform":{"x":-54.15,"y":-104.85}}]},{"name":"Layer 20","display":[{"name":"Symbol 2939","transform":{"x":-2.9,"y":9.5}}]},{"name":"Layer 11","display":[{"name":"Symbol 2931","transform":{"x":0.15,"y":0.3}}]},{"name":"Layer 7","display":[{"name":"Symbol 3113","transform":{"x":57.85,"y":0.05}}]},{"name":"Layer 18","display":[{"name":"Symbol 2943","transform":{"x":-3.8,"y":9.5}}]},{"name":"money_tx","display":[{"name":"位图 5"}]},{"name":"close_bt","display":[{"name":"Symbol 2945","transform":{"x":13.5,"y":19.9}}]},{"name":"Layer 23","display":[{"name":"Symbol 2077"}]},{"name":"slot_3","display":[{"type":"armature","name":"Symbol 3124"}]},{"name":"Layer 14","display":[{"name":"Symbol 2983","transform":{"x":16.45,"y":-72.85}}]},{"name":"Layer 10","display":[{"name":"Symbol 3108","transform":{"x":2.7,"y":1.05}}]},{"name":"Layer 21","display":[{"name":"Symbol 2937","transform":{"x":-3.15,"y":4}}]},{"name":"slot_5","display":[{"type":"armature","name":"Symbol 3124"}]},{"name":"Layer 12","display":[{"name":"Symbol 2931","transform":{"x":0.15,"y":0.3}}]},{"name":"Layer 8","display":[{"name":"Symbol 3111","transform":{"x":-10,"y":6.95}}]},{"name":"Layer 19","display":[{"name":"Symbol 2941","transform":{"x":-2.8,"y":6}}]}]}],"animation":[{"duration":0,"fadeInTime":0.3,"name":"shop_cl","slot":[{"name":"Layer 23","colorFrame":[{"duration":0,"value":{"aM":50}}]}]}],"defaultActions":[{"gotoAndPlay":"shop_cl"}]},{"type":"Armature","frameRate":30,"name":"radio","aabb":{"x":-42.09,"y":-34.1,"width":102,"height":85},"bone":[{"name":"root"},{"name":"Layer 4","parent":"root","transform":{"x":8.85,"y":8.35}},{"name":"n_tx","parent":"root","transform":{"x":8.9,"y":8.4}},{"name":"Layer 2","parent":"root","transform":{"x":8.9,"y":8.4,"scX":0.21,"scY":0.26}},{"name":"none_page_cl","parent":"root","transform":{"x":8.85,"y":8.35,"scX":1.05,"scY":1.05}}],"slot":[{"name":"Layer 4","parent":"Layer 4"},{"name":"n_tx","parent":"n_tx"},{"name":"Layer 2","parent":"Layer 2"},{"name":"none_page_cl","parent":"none_page_cl"}],"skin":[{"slot":[{"name":"Layer 2","display":[{"name":"Symbol 2695","transform":{"x":0.05}}]},{"name":"none_page_cl","display":[{"name":"Symbol 3066","transform":{"x":0.3,"y":0.25}}]},{"name":"Layer 4","display":[{"name":"__dbTextures/radio/Layer 4_0","transform":{"x":0.3,"y":0.25}},{"name":"__dbTextures/radio/Layer 4_1","transform":{"x":0.3,"y":0.25}}]},{"name":"n_tx","display":[{"name":"位图 8"}]}]}],"animation":[{"duration":5,"playTimes":0,"fadeInTime":0.3,"name":"radio_3","slot":[{"name":"Layer 4","displayFrame":[{"duration":5},{"duration":0,"value":1}]}]}],"defaultActions":[{"gotoAndPlay":"radio_3"}]},{"type":"Armature","frameRate":30,"name":"SFKLeague_fla.кнопкалупапримерочная_531","aabb":{"x":-17.15,"y":-13.4,"width":31,"height":31},"bone":[{"name":"zoom_bt","transform":{"x":-1.65,"y":1.75}}],"slot":[{"name":"zoom_bt","parent":"zoom_bt"}],"skin":[{"slot":[{"name":"zoom_bt","display":[{"name":"Symbol 3073","transform":{"y":0.35}},{"name":"Symbol 3076","transform":{"y":0.35}}]}]}],"animation":[{"duration":5,"playTimes":0,"fadeInTime":0.3,"name":"zoom_bt","slot":[{"name":"zoom_bt","displayFrame":[{"duration":5},{"duration":0,"value":1}]}]}],"defaultActions":[{"gotoAndPlay":"zoom_bt"}]},{"type":"Armature","frameRate":30,"name":"Symbol 3100","aabb":{"x":-116.05,"y":-24.1,"width":272.8,"height":47.8},"bone":[{"name":"root"},{"name":"Layer 4","parent":"root","transform":{"x":45.8,"y":-0.3}},{"name":"Layer 3","parent":"root","transform":{"x":-91.3,"y":-0.45}},{"name":"des_tx","parent":"root","transform":{"x":32.7,"y":-1.1}},{"name":"icon_cl","parent":"root","transform":{"x":-92.85,"y":-0.05}}],"slot":[{"name":"Layer 4","parent":"Layer 4"},{"name":"Layer 3","parent":"Layer 3"},{"name":"des_tx","parent":"des_tx"},{"name":"icon_cl","parent":"icon_cl"}],"skin":[{"slot":[{"name":"Layer 3","display":[{"name":"Symbol 3098","transform":{"x":-1.25,"y":0.65}}]},{"name":"des_tx","display":[{"name":"位图 7"}]},{"name":"icon_cl","display":[{"type":"armature","name":"Symbol 2238"}]},{"name":"Layer 4","display":[{"name":"__dbTextures/Symbol 3100/Layer 4_0","transform":{"x":0.45,"y":0.25}}]}]}],"animation":[{"duration":0,"fadeInTime":0.3,"name":"aboutSlot"}],"defaultActions":[{"gotoAndPlay":"aboutSlot"}]},{"type":"Armature","frameRate":30,"name":"Symbol 3077","aabb":{"x":-17.15,"y":-13.4,"width":31,"height":31},"bone":[{"name":"zoom_bt","transform":{"x":-1.65,"y":1.75}}],"slot":[{"name":"zoom_bt","parent":"zoom_bt"}],"skin":[{"slot":[{"name":"zoom_bt","display":[{"name":"Button/button 3073","transform":{"y":0.35}},{"name":"Button/button 3076","transform":{"y":0.35}}]}]}],"animation":[{"duration":5,"playTimes":0,"fadeInTime":0.3,"name":"zoom_bt","slot":[{"name":"zoom_bt","displayFrame":[{"duration":5},{"duration":0,"value":1}]}]}],"defaultActions":[{"gotoAndPlay":"zoom_bt"}]},{"type":"Armature","frameRate":30,"name":"Symbol 3124","aabb":{"x":-39.39,"y":-19.45,"width":95.94,"height":126.4},"bone":[{"name":"root"},{"name":"card_cl","parent":"root","transform":{"x":3.3}},{"name":"buy_bt","parent":"root","transform":{"x":14,"y":91.95}},{"name":"price_tx","parent":"root","transform":{"x":20.55,"y":65.65}},{"name":"Layer 2","parent":"root","transform":{"x":-24,"y":62.75,"skX":-47.45,"skY":-47.45,"scX":-0.88,"scY":0.88}},{"name":"sold_cl","parent":"root","transform":{"x":3,"skX":-20.21,"skY":-20.21}}],"slot":[{"name":"card_cl","parent":"card_cl"},{"name":"buy_bt","parent":"buy_bt"},{"name":"price_tx","parent":"price_tx"},{"name":"Layer 2","parent":"Layer 2"},{"name":"sold_cl","parent":"sold_cl"}],"skin":[{"slot":[{"name":"card_cl","display":[{"name":"card_mc","transform":{"x":0.05,"y":0.05}},{"name":"位图 1"}]},{"name":"sold_cl","display":[{"name":"Symbol 3122","transform":{"x":0.35,"y":0.45}}]},{"name":"buy_bt","display":[{"type":"armature","name":"Symbol 3118"}]},{"name":"price_tx","display":[{"name":"位图 3"}]},{"name":"Layer 2","display":[{"name":"Symbol 3120","transform":{"x":0.15,"y":0.3}}]}]}],"animation":[{"duration":5,"playTimes":0,"fadeInTime":0.3,"name":"shopSlot","bone":[{"name":"card_cl","translateFrame":[{"duration":5},{"duration":0,"x":-22.05,"y":-7.45}]}],"slot":[{"name":"sold_cl","displayFrame":[{"duration":5},{"duration":0,"value":-1}]},{"name":"Layer 2","displayFrame":[{"duration":5},{"duration":0,"value":-1}]},{"name":"price_tx","displayFrame":[{"duration":5},{"duration":0,"value":-1}]},{"name":"buy_bt","displayFrame":[{"duration":5},{"duration":0,"value":-1}]},{"name":"card_cl","displayFrame":[{"duration":5},{"duration":0,"value":1}]}]}],"defaultActions":[{"gotoAndPlay":"shopSlot"}]},{"type":"Armature","frameRate":30,"name":"Symbol 2238","aabb":{"x":-20.15,"y":-14.05,"width":37,"height":26},"bone":[{"name":"Layer 1","transform":{"x":-1.15,"y":0.35}}],"slot":[{"name":"Layer 1","parent":"Layer 1"}],"skin":[{"slot":[{"name":"Layer 1","display":[{"name":"Symbol 2208","transform":{"x":-0.5,"y":-1.4}},{"name":"Symbol 2210","transform":{"x":2.05,"y":0.2}},{"name":"Symbol 2212","transform":{"x":0.95,"y":-0.45}},{"name":"Symbol 2217","transform":{"x":0.7,"y":0.6}},{"name":"Symbol 2219","transform":{"x":9.65,"y":8.1}},{"name":"Symbol 2221","transform":{"x":3.4,"y":1.1}},{"name":"Symbol 2223","transform":{"x":3.4,"y":0.7}},{"name":"Symbol 2225","transform":{"x":9.65,"y":8.6}},{"name":"Symbol 2227","transform":{"x":8.55,"y":8.9}},{"name":"Symbol 2229","transform":{"x":9.05,"y":7.7}},{"name":"Symbol 2231","transform":{"x":9.05,"y":7.7}},{"name":"Symbol 2233","transform":{"x":9.05,"y":7.7}},{"name":"Symbol 2235","transform":{"x":9.35,"y":8.35}},{"name":"Symbol 2237","transform":{"x":1.45,"y":-0.3}}]}]}],"animation":[{"duration":14,"fadeInTime":0.3,"name":"icon_cl","bone":[{"name":"Layer 1","translateFrame":[{"duration":2},{},{"x":0.15,"y":0.5},{"x":-8.1,"y":-8.05},{},{"x":-2.1,"y":-0.35},{"x":-1.95,"y":0.55},{"x":-8.4,"y":-8.65},{"duration":3,"x":-7.6,"y":-7.8},{"x":-7.6,"y":-7.8},{"x":-8.4,"y":-8.65},{"duration":0,"x":0.15,"y":0.5}],"scaleFrame":[{"duration":5},{},{"x":0.83,"y":0.83},{"x":0.83,"y":0.83},{"duration":6}]}],"slot":[{"name":"Layer 1","displayFrame":[{},{"value":1},{"value":2},{"value":3},{"value":4},{"value":-1},{"value":5},{"value":6},{"value":7},{"value":8},{"value":9},{"value":10},{"value":11},{"value":12},{"duration":0,"value":13}]}]}],"defaultActions":[{"gotoAndPlay":"icon_cl"}]},{"type":"Armature","frameRate":30,"name":"Symbol 3118","aabb":{"x":-48.8,"y":-12.25,"width":76,"height":30},"bone":[{"name":"root"},{"name":"buy_bt","parent":"root","transform":{"x":-10.85,"y":2.3}},{"name":"Layer 1","parent":"root","transform":{"x":-10.2,"y":-1.9}}],"slot":[{"name":"buy_bt","parent":"buy_bt"},{"name":"Layer 1","parent":"Layer 1"}],"skin":[{"slot":[{"name":"buy_bt","display":[{"name":"Symbol 3116","transform":{"x":0.05,"y":0.45}},{"name":"__dbTextures/Symbol 3118/buy_bt_1","transform":{"x":0.1,"y":0.45}}]},{"name":"Layer 1","display":[{"name":"位图 2"}]}]}],"animation":[{"duration":5,"playTimes":0,"fadeInTime":0.3,"name":"buy_bt","bone":[{"name":"buy_bt","translateFrame":[{"duration":5},{"duration":0,"x":-0.05}]}],"slot":[{"name":"Layer 1","displayFrame":[{"duration":5,"value":-1},{"duration":0}]},{"name":"buy_bt","displayFrame":[{"duration":5},{"duration":0,"value":1}]}]}],"defaultActions":[{"gotoAndPlay":"buy_bt"}]}]}