{"frameRate":30,"name":"Menu","version":"5.5","compatibleVersion":"5.5","armature":[{"type":"Armature","frameRate":30,"name":"Menu","aabb":{"x":-187.2,"y":-55,"width":1119,"height":629.05},"bone":[{"name":"root"},{"name":"bg","parent":"root","transform":{"x":428.25,"y":261.55}},{"name":"clear_cl","parent":"root","transform":{"x":-7.25,"y":401.1}},{"name":"Layer 18","parent":"root","transform":{"x":331.65,"y":81.4}},{"name":"play_cl","parent":"root","transform":{"x":325,"y":368.8}},{"name":"sounds_control_cl","parent":"root","transform":{"x":592.4,"y":2}},{"name":"deqaf_bt","parent":"root","transform":{"x":4.95,"y":4.6,"scX":0.92,"scY":0.92}},{"name":"cat1","parent":"root","transform":{"x":205,"y":290.9,"scX":0.67,"scY":0.67}},{"name":"cat2","parent":"root","transform":{"x":435,"y":290.2,"scX":0.67,"scY":0.67}},{"name":"cup_5","parent":"root","transform":{"x":617.5,"y":334.45}},{"name":"cup_4","parent":"root","transform":{"x":617.6,"y":264.25}},{"name":"cup_3","parent":"root","transform":{"x":617.65,"y":197.3}},{"name":"cup_2","parent":"root","transform":{"x":617.5,"y":133.5}},{"name":"cup_1","parent":"root","transform":{"x":618.3,"y":67.2}},{"name":"Layer 7","parent":"root","transform":{"x":451.5,"y":388.2}},{"name":"face_bt","parent":"root","transform":{"x":195.25,"y":392.9}},{"name":"go_sfk1","parent":"root","transform":{"x":35.5,"y":79.95}},{"name":"go_sfk2","parent":"root","transform":{"x":38.1,"y":152}},{"name":"go_sfk3","parent":"root","transform":{"x":38,"y":226.55}},{"name":"zone_panel","parent":"root"}],"slot":[{"name":"bg","parent":"bg"},{"name":"clear_cl","parent":"clear_cl"},{"name":"Layer 18","parent":"Layer 18"},{"name":"play_cl","parent":"play_cl"},{"name":"sounds_control_cl","parent":"sounds_control_cl"},{"name":"deqaf_bt","parent":"deqaf_bt"},{"name":"cat1","parent":"cat1"},{"name":"cat2","parent":"cat2"},{"name":"cup_5","parent":"cup_5"},{"name":"cup_4","parent":"cup_4"},{"name":"cup_3","parent":"cup_3"},{"name":"cup_2","parent":"cup_2"},{"name":"cup_1","parent":"cup_1"},{"name":"Layer 7","parent":"Layer 7"},{"name":"face_bt","parent":"face_bt"},{"name":"go_sfk1","parent":"go_sfk1"},{"name":"go_sfk2","parent":"go_sfk2"},{"name":"go_sfk3","parent":"go_sfk3"},{"name":"zone_panel","parent":"zone_panel"}],"skin":[{"slot":[{"name":"Layer 7","display":[{"name":"Symbol 2687","transform":{"x":32.2,"y":29.45}}]},{"name":"clear_cl","display":[{"type":"armature","name":"Symbol 2685"}]},{"name":"play_cl","display":[{"type":"armature","name":"play_cl"}]},{"name":"go_sfk1","display":[{"type":"armature","name":"Symbol 2696"}]},{"name":"cup_3","display":[{"name":"Symbol 183","transform":{"x":2.25,"y":2.7}}]},{"name":"face_bt","display":[{"type":"armature","name":"Symbol 2692"}]},{"name":"go_sfk2","display":[{"type":"armature","name":"Symbol 2700"}]},{"name":"cat2","display":[{"name":"cat_mc","transform":{"x":0.05,"y":0.05}}]},{"name":"Layer 18","display":[{"name":"Symbol 1940","transform":{"x":-7,"y":47.65}}]},{"name":"zone_panel","display":[{"name":"Symbol 206","transform":{"x":-38.9,"y":-38}}]},{"name":"cat1","display":[{"name":"cat_mc","transform":{"x":0.05,"y":0.05}}]},{"name":"cup_2","display":[{"name":"Symbol 181","transform":{"x":1.55,"y":2.3}}]},{"name":"go_sfk3","display":[{"type":"armature","name":"Symbol 2703"}]},{"name":"deqaf_bt","display":[{"type":"armature","name":"Symbol 1903"}]},{"name":"bg","display":[{"name":"bg","transform":{"x":-55.95,"y":0.5}}]},{"name":"cup_5","display":[{"name":"Symbol 187","transform":{"x":0.3,"y":-0.2}}]},{"name":"cup_1","display":[{"name":"Symbol 189","transform":{"x":0.55,"y":1.35}}]},{"name":"sounds_control_cl","display":[{"name":"Buttons_sounds2","transform":{"x":0.05,"y":0.05}}]},{"name":"cup_4","display":[{"name":"Symbol 185","transform":{"x":0.7,"y":1.5}}]}]}],"animation":[{"duration":0,"fadeInTime":0.3,"name":"Menu"}],"defaultActions":[{"gotoAndPlay":"Menu"}]},{"type":"Armature","frameRate":30,"name":"Symbol 2685","aabb":{"x":11,"y":9,"width":42,"height":37},"bone":[{"name":"root"},{"name":"Layer 2","parent":"root"},{"name":"Layer 1","parent":"root","transform":{"x":32.05,"y":26.75,"scX":0.88,"scY":0.88}}],"slot":[{"name":"Layer 2","parent":"Layer 2"},{"name":"Layer 1","parent":"Layer 1"}],"skin":[{"slot":[{"name":"Layer 1","display":[{"name":"Symbol 2684","transform":{"x":0.1,"y":0.05}},{"name":"__dbTextures/Symbol 2685/Layer 1_3","transform":{"x":0.1,"y":0.45}}]},{"name":"Layer 2","display":[{"name":"Symbol 2682","transform":{"x":32,"y":27.5}}]}]}],"animation":[{"duration":3,"fadeInTime":0.3,"name":"clear_cl","bone":[{"name":"Layer 2","translateFrame":[{},{"x":-2.25,"y":-1.8},{}],"scaleFrame":[{},{"x":1.07,"y":1.07},{}]},{"name":"Layer 1","translateFrame":[{"duration":2},{},{"duration":0,"x":-32.05,"y":-27.15}],"scaleFrame":[{},{"x":1.07,"y":1.07},{},{"duration":0,"x":1.14,"y":1.14}]}],"slot":[{"name":"Layer 1","displayFrame":[{"duration":3},{"duration":0,"value":1}]}]}],"defaultActions":[{"gotoAndPlay":"clear_cl"}]},{"type":"Armature","frameRate":30,"name":"play_cl","aabb":{"x":-40.25,"y":-39.9,"width":80.75,"height":90.45},"bone":[{"name":"root"},{"name":"Layer 10","parent":"root"},{"name":"Layer 9","parent":"root","transform":{"x":15.2,"y":-19.8,"skX":30,"skY":30,"scX":0.52,"scY":0.52}},{"name":"Layer 8","parent":"root"},{"name":"Layer 7","parent":"root","transform":{"x":14,"y":20.9,"skX":-75,"skY":-75,"scX":0.52,"scY":0.52}},{"name":"Layer 6","parent":"root","transform":{"x":19.3,"y":24.25}},{"name":"Layer 5","parent":"root","transform":{"x":-14.8,"y":1,"skX":45,"skY":45,"scX":0.52,"scY":0.52}},{"name":"Layer 3","parent":"root","transform":{"x":-12.9,"y":-21.1,"scX":0.9,"scY":0.9}},{"name":"Layer 1","parent":"root","transform":{"x":-2.75,"y":-10.9,"scX":0.49,"scY":0.49}}],"slot":[{"name":"Layer 10","parent":"Layer 10"},{"name":"Layer 9","parent":"Layer 9"},{"name":"Layer 8","parent":"Layer 8"},{"name":"Layer 7","parent":"Layer 7"},{"name":"Layer 6","parent":"Layer 6"},{"name":"Layer 5","parent":"Layer 5"},{"name":"Layer 3","parent":"Layer 3"},{"name":"Layer 1","parent":"Layer 1"}],"skin":[{"slot":[{"name":"Layer 1","display":[{"name":"Symbol 175","transform":{"x":0.2,"y":0.2}}]},{"name":"Layer 9","display":[{"name":"Symbol 171","transform":{"x":0.25,"y":0.25}},{"name":"__dbTextures/play_cl/Layer 9_3","transform":{"x":0.25,"y":0.25}}]},{"name":"Layer 6","display":[{"name":"__dbTextures/play_cl/Layer 6_3","transform":{"x":0.2,"y":0.3}}]},{"name":"Layer 7","display":[{"name":"Symbol 171","transform":{"x":0.25,"y":0.25}},{"name":"__dbTextures/play_cl/Layer 7_3","transform":{"x":0.25,"y":0.25}}]},{"name":"Layer 8","display":[{"name":"__dbTextures/play_cl/Layer 8_3","transform":{"x":0.25,"y":0.25}}]},{"name":"Layer 3","display":[{"name":"Symbol 173","transform":{"x":19.5,"y":24.55}}]},{"name":"Layer 5","display":[{"name":"Symbol 171","transform":{"x":0.25,"y":0.25}},{"name":"Symbol 174","transform":{"x":0.05,"y":0.05}}]},{"name":"Layer 10","display":[{"name":"Symbol 169","transform":{"x":-0.25,"y":0.1}},{"name":"Symbol 176","transform":{"x":0.05,"y":0.4}},{"name":"Symbol 177","transform":{"x":-0.1,"y":0.25}}]}]}],"animation":[{"duration":3,"fadeInTime":0.3,"name":"play_cl","bone":[{"name":"Layer 9","translateFrame":[{},{"x":1.7,"y":-2.2},{"x":-0.45,"y":0.6},{"duration":0,"x":-15.2,"y":19.8}],"rotateFrame":[{"duration":2},{},{"duration":0,"rotate":-30}],"scaleFrame":[{},{"x":1.12,"y":1.12},{"x":0.98,"y":0.98},{"duration":0,"x":1.92,"y":1.92}]},{"name":"Layer 7","translateFrame":[{},{"x":1.6,"y":2.3},{"x":-0.4,"y":-0.65},{"duration":0,"x":-14,"y":-20.9}],"rotateFrame":[{"duration":2},{},{"duration":0,"rotate":75}],"scaleFrame":[{},{"x":1.12,"y":1.12},{"x":0.98,"y":0.98},{"duration":0,"x":1.92,"y":1.92}]},{"name":"Layer 5","translateFrame":[{},{"x":-1.6,"y":0.1},{"x":0.45,"y":-0.05},{"duration":0,"x":12.05,"y":-11.9}],"rotateFrame":[{"duration":2},{},{"duration":0,"rotate":-45}],"scaleFrame":[{},{"x":1.12,"y":1.12},{"x":0.98,"y":0.98},{"duration":0,"x":1.23,"y":1.23}]},{"name":"Layer 3","translateFrame":[{},{"x":-1.35,"y":-2.3},{"x":0.4,"y":0.65},{"duration":0}],"scaleFrame":[{},{"x":1.11,"y":1.11},{"x":0.97,"y":0.97},{"duration":0}]},{"name":"Layer 1","translateFrame":[{},{"x":-0.25,"y":-1.2},{"x":0.1,"y":0.35},{"duration":0}],"scaleFrame":[{},{"x":1.12,"y":1.12},{"x":0.98,"y":0.98},{"duration":0}]}],"slot":[{"name":"Layer 1","displayFrame":[{"duration":3},{"duration":0,"value":-1}],"colorFrame":[{"duration":2,"value":{"aM":65}},{"value":{"aM":65}},{"duration":0}]},{"name":"Layer 3","displayFrame":[{"duration":3},{"duration":0,"value":-1}]},{"name":"Layer 5","displayFrame":[{"duration":3},{"duration":0,"value":1}],"colorFrame":[{"duration":2,"value":{"rM":5,"gM":5,"bM":5,"rO":219,"gO":121}},{"value":{"rM":5,"gM":5,"bM":5,"rO":219,"gO":121}},{"duration":0,"value":{"aM":65}}]},{"name":"Layer 6","displayFrame":[{"duration":3,"value":-1},{"duration":0}]},{"name":"Layer 7","displayFrame":[{"duration":3},{"duration":0,"value":1}],"colorFrame":[{"duration":2,"value":{"rM":5,"gM":5,"bM":5,"rO":219,"gO":121}},{"value":{"rM":5,"gM":5,"bM":5,"rO":219,"gO":121}},{"duration":0}]},{"name":"Layer 8","displayFrame":[{"duration":3,"value":-1},{"duration":0}]},{"name":"Layer 9","displayFrame":[{"duration":3},{"duration":0,"value":1}],"colorFrame":[{"duration":2,"value":{"rM":5,"gM":5,"bM":5,"rO":219,"gO":121}},{"value":{"rM":5,"gM":5,"bM":5,"rO":219,"gO":121}},{"duration":0}]},{"name":"Layer 10","displayFrame":[{},{"value":1},{"value":2},{"duration":0}]}]}],"defaultActions":[{"gotoAndPlay":"play_cl"}]},{"type":"Armature","frameRate":30,"name":"Symbol 1903","aabb":{"x":-1,"y":-1,"width":40,"height":40},"bone":[{"name":"Layer 1"}],"slot":[{"name":"Layer 1","parent":"Layer 1"}],"skin":[{"slot":[{"name":"Layer 1","display":[{"name":"Symbol 1898","transform":{"x":19,"y":19}},{"name":"Symbol 1899","transform":{"x":18.65,"y":19.1}},{"name":"Symbol 1901","transform":{"x":17.05,"y":19.95}}]}]}],"animation":[{"duration":3,"fadeInTime":0.3,"name":"deqaf_bt","slot":[{"name":"Layer 1","displayFrame":[{},{"value":1},{},{"duration":0,"value":2}]}]}],"defaultActions":[{"gotoAndPlay":"deqaf_bt"}]},{"type":"Armature","frameRate":30,"name":"Symbol 2692","aabb":{"x":-61.6,"y":3.3,"width":124,"height":44},"bone":[{"name":"root"},{"name":"Layer 2","parent":"root","transform":{"y":25.25}},{"name":"face_bt","parent":"root","transform":{"x":-38.5,"y":24.5,"scX":0.51,"scY":0.51}}],"slot":[{"name":"Layer 2","parent":"Layer 2"},{"name":"face_bt","parent":"face_bt"}],"skin":[{"slot":[{"name":"Layer 2","display":[{"name":"__dbTextures/Symbol 2692/Layer 2_0","transform":{"x":0.4,"y":0.05}}]},{"name":"face_bt","display":[{"type":"armature","name":"Symbol 2691"}]}]}],"animation":[{"duration":0,"fadeInTime":0.3,"name":"face_bt"}],"defaultActions":[{"gotoAndPlay":"face_bt"}]},{"type":"Armature","frameRate":30,"name":"Symbol 2696","aabb":{"x":-50.97,"y":-42.5,"width":102,"height":85},"bone":[{"name":"root"},{"name":"Layer 2","parent":"root"},{"name":"Layer 1","parent":"root","transform":{"scX":0.59,"scY":0.71}}],"slot":[{"name":"Layer 2","parent":"Layer 2"},{"name":"Layer 1","parent":"Layer 1"}],"skin":[{"slot":[{"name":"Layer 1","display":[{"name":"Symbol 2695","transform":{"x":0.05}}]},{"name":"Layer 2","display":[{"name":"__dbTextures/Symbol 2696/Layer 2_0"}]}]}],"animation":[{"duration":0,"fadeInTime":0.3,"name":"go_sfk1"}],"defaultActions":[{"gotoAndPlay":"go_sfk1"}]},{"type":"Armature","frameRate":30,"name":"Symbol 2700","aabb":{"x":-50.97,"y":-42.5,"width":102,"height":85},"bone":[{"name":"root"},{"name":"bg","parent":"root"},{"name":"mask","parent":"root"},{"name":"Layer 1","parent":"root","transform":{"scX":0.59,"scY":0.71}}],"slot":[{"name":"bg","parent":"bg"},{"name":"mask","parent":"mask"},{"name":"Layer 1","parent":"Layer 1"}],"skin":[{"slot":[{"name":"bg","display":[{"name":"__dbTextures/Symbol 2700/bg_0"}]},{"name":"mask","display":[{"name":"Symbol 2697","transform":{"x":0.25,"y":0.25}}]},{"name":"Layer 1","display":[{"name":"Symbol 2695","transform":{"x":0.05}}]}]}],"animation":[{"duration":0,"fadeInTime":0.3,"name":"go_sfk2"}],"defaultActions":[{"gotoAndPlay":"go_sfk2"}]},{"type":"Armature","frameRate":30,"name":"Symbol 2703","aabb":{"x":-50.97,"y":-42.5,"width":102,"height":85},"bone":[{"name":"root"},{"name":"bg","parent":"root"},{"name":"mask","parent":"root"},{"name":"Layer 1","parent":"root","transform":{"scX":0.59,"scY":0.71}}],"slot":[{"name":"bg","parent":"bg"},{"name":"mask","parent":"mask"},{"name":"Layer 1","parent":"Layer 1"}],"skin":[{"slot":[{"name":"mask","display":[{"name":"Symbol 2697","transform":{"x":0.25,"y":0.25}}]},{"name":"Layer 1","display":[{"name":"Symbol 2695","transform":{"x":0.05}}]},{"name":"bg","display":[{"name":"__dbTextures/Symbol 2703/bg_0"}]}]}],"animation":[{"duration":0,"fadeInTime":0.3,"name":"go_sfk3"}],"defaultActions":[{"gotoAndPlay":"go_sfk3"}]},{"type":"Armature","frameRate":30,"name":"Symbol 2691","aabb":{"x":-31.5,"y":-35.18,"width":218.4,"height":66.68},"bone":[{"name":"root"},{"name":"Layer 4","parent":"root"},{"name":"Layer 3","parent":"root","transform":{"x":8.95,"y":-17.2,"scX":0.43,"scY":0.43}},{"name":"Layer 2","parent":"root","transform":{"x":8.95,"y":-17.2,"scX":0.46,"scY":0.46}},{"name":"Layer 1","parent":"root","transform":{"x":110.9,"y":-1.5}}],"slot":[{"name":"Layer 4","parent":"Layer 4"},{"name":"Layer 3","parent":"Layer 3"},{"name":"Layer 2","parent":"Layer 2"},{"name":"Layer 1","parent":"Layer 1"}],"skin":[{"slot":[{"name":"Layer 2","display":[{"name":"Symbol 174","transform":{"x":0.05,"y":0.05}}]},{"name":"Layer 1","display":[{"name":"位图 1"},{"name":"text","transform":{"x":-2,"y":-2}}]},{"name":"Layer 4","display":[{"name":"Symbol 1879"},{"name":"Symbol 1881","transform":{"x":-0.7,"y":1.4}},{"name":"Symbol 1882","transform":{"x":0.65,"y":-0.05}}]},{"name":"Layer 3","display":[{"name":"Symbol 1880","transform":{"x":0.05,"y":0.05}},{"name":"Symbol 2690","transform":{"x":72.15,"y":-0.05}}]}]}],"animation":[{"duration":3,"fadeInTime":0.3,"name":"face_bt","bone":[{"name":"Layer 3","translateFrame":[{"duration":2},{},{"duration":0,"x":-8.95,"y":17.2}],"scaleFrame":[{},{"x":1.07,"y":1.07},{"x":0.98,"y":0.98},{"duration":0,"x":2.33,"y":2.33}]},{"name":"Layer 1","translateFrame":[{},{"duration":2,"x":-2.35,"y":-2}],"scaleFrame":[{},{"duration":2,"x":2.65,"y":2.36}]}],"slot":[{"name":"Layer 1","displayFrame":[{},{"duration":2,"value":1}]},{"name":"Layer 2","displayFrame":[{"duration":3,"value":-1},{"duration":0}],"colorFrame":[{"duration":3},{"duration":0,"value":{"aM":80}}]},{"name":"Layer 3","displayFrame":[{"duration":3},{"duration":0,"value":1}],"colorFrame":[{"duration":2,"value":{"aM":80}},{"value":{"aM":80}},{"duration":0}]},{"name":"Layer 4","displayFrame":[{},{"value":1},{"value":2},{"duration":0,"value":-1}]}]}],"defaultActions":[{"gotoAndPlay":"face_bt"}]}]}